disvortilo/__init__.py
disvortilo/full_words.txt
disvortilo/prefixes.txt
disvortilo/roots.txt
disvortilo/suffixes.txt
disvortilo-0.1.0.dist-info/licenses/LICENSE
disvortilo-0.1.0.dist-info/METADATA
disvortilo-0.1.0.dist-info/WHEEL
disvortilo-0.1.0.dist-info/top_level.txt
disvortilo-0.1.0.dist-info/RECORD
