Metadata-Version: 2.4
Name: disvortilo
Version: 0.1.0
Summary: Disvortilo is a simple tool that breaks Esperanto words into roots and affixes.
Author-email: Franz Weingartz <scaui0@gmx.net>
License-Expression: MIT
Project-URL: Homepage, https://github.com/LerniloEO/disvortilo
Project-URL: Repository, https://github.com/LerniloEO/disvortilo
Project-URL: Issues, https://github.com/LerniloEO/disvortilo/issues
Keywords: Esperanto,morphology,linguistics,NLP
Classifier: Topic :: Text Processing :: Linguistic
Classifier: Operating System :: OS Independent
Classifier: Programming Language :: Python :: 3
Requires-Python: >=3.9
License-File: LICENSE
Dynamic: license-file
